{
    "course_name": "肉屋コース",
    "price": 6000,
    "description": "黒毛和牛が食べ放題に！ソフトドリンク飲み放題つきの焼肉食べ放題コース！",
    "order_time": 80,
    "seat_time": 20,
    "dishes_": [
        {
            "id": "nk1",
            "name": "特選牛タン",
            "name_en": "special beef tongue",
            "quantity": 1
        },
        {
            "id": "nk2",
            "name": "上カルビ",
            "name_en": "premium beef rib",
            "quantity": 2
        },
        {
            "id": "nk3",
            "name": "ロース",
            "name_en": "beef loin",
            "quantity": 1
        },
        {
            "id": "nk4",
            "name": "豚トロ",
            "name_en": "pork toro",
            "quantity": 1
        },
        {
            "id": "nk5",
            "name": "キムチ盛り合わせ",
            "name_en": "kimchi assortment",
            "quantity": 1
        },
        {
            "id": "nk6",
            "name": "サンチュ",
            "name_en": "sangchu",
            "quantity": 1
        }
    ]
} 